ally/Ally.py
ally/Api.py
ally/Auth.py
ally/Info.py
ally/RateLimit.py
ally/__init__.py
ally/classes.py
ally/exception.py
ally/tests.py
ally/Account/__init__.py
ally/Account/accounts.py
ally/Account/balances.py
ally/Account/history.py
ally/Account/holdings.py
ally/Account/utils.py
ally/News/Lookup.py
ally/News/Search.py
ally/News/__init__.py
ally/Option/__init__.py
ally/Option/classes.py
ally/Option/expirations.py
ally/Option/search.py
ally/Option/strikes.py
ally/Order/Outstanding.py
ally/Order/Submit.py
ally/Order/__init__.py
ally/Order/classes.py
ally/Order/order.py
ally/Order/utils.py
ally/Order/tests/InstrumentConstruction.py
ally/Order/tests/OrderConstruction.py
ally/Order/tests/OrderManual.py
ally/Order/tests/OrderParse.py
ally/Order/tests/OrderSubmition.py
ally/Order/tests/PricingConstruction.py
ally/Order/tests/__init__.py
ally/Order/tests/classes.py
ally/Quote/__init__.py
ally/Quote/quote.py
ally/Quote/stream.py
ally/Quote/timesales.py
ally/Quote/toplists.py
ally/Watchlist/__init__.py
ally/Watchlist/methods.py
ally/utils/__init__.py
ally/utils/json.py
ally/utils/option.py
ally/utils/tests.py
ally/utils/utils.py
pyally-1.1.2.dist-info/LICENSE
pyally-1.1.2.dist-info/METADATA
pyally-1.1.2.dist-info/WHEEL
pyally-1.1.2.dist-info/top_level.txt
pyally-1.1.2.dist-info/RECORD
