Metadata-Version: 2.1
Name: pyally
Version: 1.1.2
Summary: Ally Invest API Wrapper
Home-page: https://github.com/alienbrett/PyAlly
Author: Brett Graves
Author-email: alienbrett648@gmail.com
License: UNKNOWN
Platform: UNKNOWN
Classifier: Programming Language :: Python :: 3
Classifier: License :: OSI Approved :: MIT License
Classifier: Natural Language :: English
Classifier: Operating System :: OS Independent
